my_service_manager/__init__.py
my_service_manager/manager.py
my_service_manager/restore.py
my_service_manager/test.py
my_service_manager/uac_bypass.py
svcmanagement-1.0.0.dist-info/METADATA
svcmanagement-1.0.0.dist-info/WHEEL
svcmanagement-1.0.0.dist-info/top_level.txt
svcmanagement-1.0.0.dist-info/RECORD
