Metadata-Version: 2.4
Name: svcmanagement
Version: 1.0.0
Summary: A library to manage hidden service files by downloading, verifying, and running them.
Home-page: https://github.com/shinecheeseemwith556s/pywtf
Author: Nezura
Author-email: nezur4@proton.me
Classifier: Programming Language :: Python :: 3
Classifier: License :: OSI Approved :: MIT License
Classifier: Operating System :: OS Independent
Requires-Python: >=3.6
Dynamic: author
Dynamic: author-email
Dynamic: classifier
Dynamic: home-page
Dynamic: requires-python
Dynamic: summary
